eth_utils/__init__.py
eth_utils/__main__.py
eth_utils/abi.py
eth_utils/address.py
eth_utils/applicators.py
eth_utils/conversions.py
eth_utils/crypto.py
eth_utils/currency.py
eth_utils/debug.py
eth_utils/decorators.py
eth_utils/encoding.py
eth_utils/exceptions.py
eth_utils/functional.py
eth_utils/hexadecimal.py
eth_utils/humanize.py
eth_utils/logging.py
eth_utils/module_loading.py
eth_utils/network.py
eth_utils/numeric.py
eth_utils/py.typed
eth_utils/toolz.py
eth_utils/types.py
eth_utils/units.py
eth_utils/__json/eth_networks.json
eth_utils/curried/__init__.py
eth_utils/typing/__init__.py
eth_utils/typing/misc.py
eth_utils-5.2.0.dist-info/LICENSE
eth_utils-5.2.0.dist-info/METADATA
eth_utils-5.2.0.dist-info/WHEEL
eth_utils-5.2.0.dist-info/top_level.txt
eth_utils-5.2.0.dist-info/RECORD
