Metadata-Version: 2.1
Name: eth-utils
Version: 5.2.0
Summary: eth-utils: Common utility functions for python code that interacts with Ethereum
Home-page: https://github.com/ethereum/eth-utils
Author: The Ethereum Foundation
Author-email: snakecharmers@ethereum.org
License: MIT
Keywords: ethereum
Classifier: Intended Audience :: Developers
Classifier: License :: OSI Approved :: MIT License
Classifier: Natural Language :: English
Classifier: Programming Language :: Python :: 3
Classifier: Programming Language :: Python :: 3.8
Classifier: Programming Language :: Python :: 3.9
Classifier: Programming Language :: Python :: 3.10
Classifier: Programming Language :: Python :: 3.11
Classifier: Programming Language :: Python :: 3.12
Classifier: Programming Language :: Python :: 3.13
Requires-Python: >=3.8, <4
License-File: LICENSE
Requires-Dist: eth-hash>=0.3.1
Requires-Dist: eth-typing>=5.0.0
Requires-Dist: toolz>0.8.2; implementation_name == "pypy"
Requires-Dist: cytoolz>=0.10.1; implementation_name == "cpython"
Provides-Extra: dev
Requires-Dist: build>=0.9.0; extra == "dev"
Requires-Dist: bump_my_version>=0.19.0; extra == "dev"
Requires-Dist: eth-hash[pycryptodome]; extra == "dev"
Requires-Dist: ipython; extra == "dev"
Requires-Dist: mypy==1.10.0; extra == "dev"
Requires-Dist: pre-commit>=3.4.0; extra == "dev"
Requires-Dist: tox>=4.0.0; extra == "dev"
Requires-Dist: twine; extra == "dev"
Requires-Dist: wheel; extra == "dev"
Requires-Dist: sphinx>=6.0.0; extra == "dev"
Requires-Dist: sphinx-autobuild>=2021.3.14; extra == "dev"
Requires-Dist: sphinx_rtd_theme>=1.0.0; extra == "dev"
Requires-Dist: towncrier<25,>=24; extra == "dev"
Requires-Dist: hypothesis>=4.43.0; extra == "dev"
Requires-Dist: mypy==1.10.0; extra == "dev"
Requires-Dist: pytest>=7.0.0; extra == "dev"
Requires-Dist: pytest-xdist>=2.4.0; extra == "dev"
Provides-Extra: docs
Requires-Dist: sphinx>=6.0.0; extra == "docs"
Requires-Dist: sphinx-autobuild>=2021.3.14; extra == "docs"
Requires-Dist: sphinx_rtd_theme>=1.0.0; extra == "docs"
Requires-Dist: towncrier<25,>=24; extra == "docs"
Provides-Extra: test
Requires-Dist: hypothesis>=4.43.0; extra == "test"
Requires-Dist: mypy==1.10.0; extra == "test"
Requires-Dist: pytest>=7.0.0; extra == "test"
Requires-Dist: pytest-xdist>=2.4.0; extra == "test"
